pm_studio_mcp/__init__.py
pm_studio_mcp/__main__.py
pm_studio_mcp/config.py
pm_studio_mcp/constant.py
pm_studio_mcp/server.py
pm_studio_mcp/skills/__init__.py
pm_studio_mcp/skills/greeting.py
pm_studio_mcp/utils/__init__.py
pm_studio_mcp/utils/crawl_utils.py
pm_studio_mcp/utils/data_visualization_utils.py
pm_studio_mcp/utils/file_utils.py
pm_studio_mcp/utils/key_vault_utils.py
pm_studio_mcp/utils/matching_utils.py
pm_studio_mcp/utils/search_utils.py
pm_studio_mcp/utils/titan_metadata_utils.py
pm_studio_mcp/utils/titan_query_utils.py
pm_studio_mcp/utils/titan_table_metadata.py
pm_studio_mcp/utils/azure_ai/__init__.py
pm_studio_mcp/utils/azure_ai/azure_inference_client.py
pm_studio_mcp/utils/azure_ai/test_azure_inference_client.py
pm_studio_mcp/utils/graph/auth.py
pm_studio_mcp/utils/graph/calendar.py
pm_studio_mcp/utils/graph/chat.py
pm_studio_mcp/utils/titan_tables/KPI_BrowserMinutes_All.py
pm_studio_mcp/utils/titan_tables/KPI_DailyUser.py
pm_studio_mcp/utils/titan_tables/__init__.py
pm_studio_mcp/utils/titan_tables/edgemacecsretentionv1.py
pm_studio_mcp/utils/titan_tables/table_metadata.py
pm_studio_mcp_nanyin-0.1.0.dist-info/METADATA
pm_studio_mcp_nanyin-0.1.0.dist-info/WHEEL
pm_studio_mcp_nanyin-0.1.0.dist-info/entry_points.txt
pm_studio_mcp_nanyin-0.1.0.dist-info/top_level.txt
pm_studio_mcp_nanyin-0.1.0.dist-info/RECORD
