Metadata-Version: 2.4
Name: pm-studio-mcp-nanyin
Version: 0.1.0
Summary: PM Studio MCP Server - A Model Context Protocol server for product managers
Requires-Python: >=3.13
Requires-Dist: fastmcp
Requires-Dist: googlesearch-python
Requires-Dist: matplotlib
Requires-Dist: seaborn
Requires-Dist: pandas
Requires-Dist: numpy
Requires-Dist: markdown
Requires-Dist: markitdown[all]
Requires-Dist: praw>=7.7.0
Requires-Dist: crawl4ai>=0.6.2
Requires-Dist: msal
Requires-Dist: azure-identity>=1.21.0
Requires-Dist: azure-ai-inference>=1.0.0b9
Requires-Dist: azure-keyvault-secrets>=4.7.0
